zoomtools/__init__.py
zoomtools-1.11.dist-info/LICENSE
zoomtools-1.11.dist-info/METADATA
zoomtools-1.11.dist-info/WHEEL
zoomtools-1.11.dist-info/top_level.txt
zoomtools-1.11.dist-info/RECORD
